g1_monetary_license/g1_monetary_license_ca.rst
g1_monetary_license/g1_monetary_license_de.rst
g1_monetary_license/g1_monetary_license_en.rst
g1_monetary_license/g1_monetary_license_eo.rst
g1_monetary_license/g1_monetary_license_es.rst
g1_monetary_license/g1_monetary_license_fr.rst
g1_monetary_license/g1_monetary_license_it.rst
g1_monetary_license/g1_monetary_license_pt.rst
silkaj/__init__.py
silkaj/about.py
silkaj/account_storage.py
silkaj/auth.py
silkaj/blockchain/__init__.py
silkaj/blockchain/blocks.py
silkaj/blockchain/difficulty.py
silkaj/blockchain/information.py
silkaj/blockchain/tools.py
silkaj/checksum.py
silkaj/cli.py
silkaj/constants.py
silkaj/g1_monetary_license.py
silkaj/money/__init__.py
silkaj/money/balance.py
silkaj/money/history.py
silkaj/money/tools.py
silkaj/money/transfer.py
silkaj/network.py
silkaj/public_key.py
silkaj/tools.py
silkaj/tui.py
silkaj/wot/__init__.py
silkaj/wot/certify.py
silkaj/wot/exclusions.py
silkaj/wot/idty_tools.py
silkaj/wot/lookup.py
silkaj/wot/membership.py
silkaj/wot/revocation.py
silkaj/wot/status.py
silkaj/wot/tools.py
silkaj-0.12.1.dist-info/AUTHORS.md
silkaj-0.12.1.dist-info/LICENSE
silkaj-0.12.1.dist-info/METADATA
silkaj-0.12.1.dist-info/WHEEL
silkaj-0.12.1.dist-info/entry_points.txt
silkaj-0.12.1.dist-info/RECORD
