Metadata-Version: 2.3
Name: silkaj
Version: 0.12.1
Summary: Command line client for Ğ1 libre-currency powered by Duniter
License: AGPL-3.0-or-later
Keywords: g1,duniter,cryptocurrency,librecurrency,RTM
Author: Moul, Maël Azimi
Author-email: mael.azimi@moul.re
Maintainer: Moul, Maël Azimi
Maintainer-email: mael.azimi@moul.re
Requires-Python: >=3.9,<4.0
Classifier: Development Status :: 5 - Production/Stable
Classifier: Environment :: Console
Classifier: Intended Audience :: End Users/Desktop
Classifier: License :: OSI Approved :: GNU Affero General Public License v3 or later (AGPLv3+)
Classifier: Natural Language :: English
Classifier: Operating System :: Unix
Classifier: Programming Language :: Python :: 3
Classifier: Programming Language :: Python :: 3.9
Classifier: Programming Language :: Python :: 3.10
Classifier: Programming Language :: Python :: 3.11
Classifier: Programming Language :: Python :: 3.12
Classifier: Programming Language :: Python :: 3.13
Provides-Extra: deathreaper
Requires-Dist: duniterpy (>=1.2.1,<1.3.0)
Requires-Dist: pendulum (>=3.1.0,<4.0.0)
Requires-Dist: pydiscourse (>=1.7.0,<2.0) ; extra == "deathreaper"
Requires-Dist: rich-click (>=1.8.8,<2.0.0)
Requires-Dist: texttable (>=1.7.0,<2.0.0)
Project-URL: Documentation, https://silkaj.duniter.org/latest/
Project-URL: Homepage, https://silkaj.duniter.org
Project-URL: Repository, https://git.duniter.org/clients/python/silkaj
Project-URL: changelog, https://silkaj.duniter.org/latest/changelog/
